microosc.py
circuitpython_microosc-0.6.dist-info/licenses/LICENSE
circuitpython_microosc-0.6.dist-info/METADATA
circuitpython_microosc-0.6.dist-info/WHEEL
circuitpython_microosc-0.6.dist-info/top_level.txt
circuitpython_microosc-0.6.dist-info/RECORD
