Metadata-Version: 2.4
Name: circuitpython-microosc
Version: 0.6
Summary: Minimal OSC parser and server for CircuitPython and CPython
Author-email: Tod Kurt <tod@todbot.com>
License: MIT
Project-URL: Homepage, https://github.com/todbot/CircuitPython_MicroOSC
Keywords: adafruit,blinka,circuitpython,micropython,microosc,OSC,MIDI,OpenSoundControl,protocol,UDP,multicast
Classifier: Intended Audience :: Developers
Classifier: Topic :: Software Development :: Libraries
Classifier: Topic :: Software Development :: Embedded Systems
Classifier: Topic :: System :: Hardware
Classifier: License :: OSI Approved :: MIT License
Classifier: Programming Language :: Python :: 3
License-File: LICENSE
Requires-Dist: Adafruit-Blinka
Provides-Extra: optional
Dynamic: license-file
